README.md
setup.py
piwebapi/__init__.py
piwebapi/attribute.py
piwebapi/config.py
piwebapi/element.py
piwebapi/picache.py
piwebapi/piobject.py
piwebapi/point.py
piwebapi.egg-info/PKG-INFO
piwebapi.egg-info/SOURCES.txt
piwebapi.egg-info/dependency_links.txt
piwebapi.egg-info/not-zip-safe
piwebapi.egg-info/requires.txt
piwebapi.egg-info/top_level.txt