Metadata-Version: 1.0
Name: piwebapi
Version: 1.0
Summary: Vitens PI Wrapper
Home-page: https://github.com/AbelHeinsbroek/piwebapi
Author: Abel Heinsbroek
Author-email: abel.heinsbroek@vitens.nl
License: Apache Licence 2.0
Platform: UNKNOWN
